simplesrp/__init__.py
simplesrp/ng_values.py
simplesrp/utils.py
simplesrp/client/__init__.py
simplesrp/client/srp.py
simplesrp/server/__init__.py
simplesrp/server/srp.py
simplesrp-1.0.0b1.dist-info/METADATA
simplesrp-1.0.0b1.dist-info/WHEEL
simplesrp-1.0.0b1.dist-info/namespace_packages.txt
simplesrp-1.0.0b1.dist-info/top_level.txt
simplesrp-1.0.0b1.dist-info/RECORD
