Metadata-Version: 2.1
Name: simplesrp
Version: 1.0.0b1
Summary: A python implementation of SRP-6a in pure python.
Home-page: https://github.com/RuslanUC/SimpleSRP
Author: RuslanUC
License: MIT
Platform: Any
Classifier: Operating System :: OS Independent
Classifier: License :: OSI Approved :: MIT License
Classifier: Programming Language :: Python
Classifier: Programming Language :: Python :: 3
Classifier: Programming Language :: Python :: 3.7
Classifier: Programming Language :: Python :: 3.8
Classifier: Programming Language :: Python :: 3.9
Classifier: Programming Language :: Python :: 3.10
Classifier: Programming Language :: Python :: 3.11
Classifier: Intended Audience :: Developers
Classifier: Environment :: Console
Requires-Python: >=3.7
